auth365/__init__.py
auth365/exceptions.py
auth365/fastapi/__init__.py
auth365/fastapi/transport.py
auth365/jwt.py
auth365/providers/__init__.py
auth365/providers/base.py
auth365/providers/google.py
auth365/providers/telegram.py
auth365/providers/yandex.py
auth365/py.typed
auth365/schemas.py
auth365/utils.py
auth365-0.1.2.dist-info/METADATA
auth365-0.1.2.dist-info/WHEEL
auth365-0.1.2.dist-info/RECORD
